riveter/__init__.py
riveter/_version.py
riveter/changelog_processor.py
riveter/cli.py
riveter/cloud_parsers.py
riveter/config.py
riveter/exceptions.py
riveter/extract_config.py
riveter/formatters.py
riveter/lazy_imports.py
riveter/logging.py
riveter/operators.py
riveter/performance.py
riveter/reporter.py
riveter/rule_distribution.py
riveter/rule_filter.py
riveter/rule_linter.py
riveter/rule_packs.py
riveter/rule_repository.py
riveter/rules.py
riveter/scanner.py
riveter/toml_handler.py
riveter/version.py
riveter/version_manager.py
riveter/version_validator.py
riveter-0.13.14.dist-info/METADATA
riveter-0.13.14.dist-info/WHEEL
riveter-0.13.14.dist-info/entry_points.txt
riveter-0.13.14.dist-info/licenses/LICENSE
riveter-0.13.14.dist-info/RECORD
