Metadata-Version: 2.4
Name: riveter
Version: 0.13.14
Summary: Infrastructure Drift Detection as Code - Define custom drift detection rules
Author: Riveter Team
License-File: LICENSE
Classifier: Development Status :: 4 - Beta
Classifier: Environment :: Console
Classifier: Intended Audience :: Developers
Classifier: Intended Audience :: System Administrators
Classifier: Topic :: Software Development :: Testing
Classifier: Topic :: System :: Systems Administration
Requires-Python: >=3.12
Requires-Dist: click>=8.0
Requires-Dist: cryptography>=41.0
Requires-Dist: python-hcl2>=4.0
Requires-Dist: pyyaml>=6.0
Requires-Dist: requests>=2.25.0
Requires-Dist: rich>=13.0
Provides-Extra: dev
Requires-Dist: bandit>=1.7.10; extra == 'dev'
Requires-Dist: black>=24.0; extra == 'dev'
Requires-Dist: importlib-metadata>=6.0; extra == 'dev'
Requires-Dist: isort>=5.13; extra == 'dev'
Requires-Dist: mypy>=1.13; extra == 'dev'
Requires-Dist: pre-commit>=3.0.0; extra == 'dev'
Requires-Dist: pyinstaller>=6.0.0; extra == 'dev'
Requires-Dist: pytest-cov>=4.0; extra == 'dev'
Requires-Dist: pytest>=7.0; extra == 'dev'
Requires-Dist: ruff>=0.8.0; extra == 'dev'
Requires-Dist: tomli-w>=1.0.0; extra == 'dev'
Requires-Dist: types-pyyaml>=6.0; extra == 'dev'
